longstaff_schwartz/__init__.py
longstaff_schwartz/algorithm.py
longstaff_schwartz/binomial.py
longstaff_schwartz/cli.py
longstaff_schwartz/regression_basis.py
longstaff_schwartz/stochastic_process.py
longstaff_schwartz-0.2.0.dist-info/AUTHORS.rst
longstaff_schwartz-0.2.0.dist-info/LICENSE
longstaff_schwartz-0.2.0.dist-info/METADATA
longstaff_schwartz-0.2.0.dist-info/WHEEL
longstaff_schwartz-0.2.0.dist-info/entry_points.txt
longstaff_schwartz-0.2.0.dist-info/top_level.txt
longstaff_schwartz-0.2.0.dist-info/RECORD
