Metadata-Version: 2.1
Name: longstaff-schwartz
Version: 0.2.0
Summary: A Python implementation of the Longstaff-Schwartz linear regression algorithm for the evaluation of call rights and American options.
Home-page: https://github.com/luphord/longstaff_schwartz
Author: luphord
Author-email: luphord@protonmail.com
License: MIT license
Keywords: longstaff_schwartz
Classifier: Development Status :: 3 - Alpha
Classifier: Intended Audience :: Developers
Classifier: License :: OSI Approved :: MIT License
Classifier: Natural Language :: English
Classifier: Programming Language :: Python :: 3
Classifier: Programming Language :: Python :: 3.8
Classifier: Programming Language :: Python :: 3.9
Classifier: Programming Language :: Python :: 3.10
License-File: LICENSE
License-File: AUTHORS.rst
Requires-Dist: Click (>=8.0)
Requires-Dist: numpy (>=1.22)
Requires-Dist: scipy (>=1.7)
Requires-Dist: matplotlib (>=3.5)
Requires-Dist: jupyterlab (>=3.5)
